<?xml version = "1.0" encoding="Windows-1256" standalone="yes"?>
<VFPData>
	<mfactone_scx_ar row_key="_1340OU2UB" cproperty="Caption" orgtext="Actualization Date                                                                                                                                                                                      " orgcol="ariaformset.AriaForm1.lblOperation" langtext="ÊÇÑíÎ ÇáÅÏÑÇß"/>
	<mfactone_scx_ar row_key="_0V1117HJ9" cproperty="Caption" orgtext="Budget                                                                                                                                                                                                  " orgcol="ariaformset.AriaForm1.lblBudget" langtext="ãæÇÒäÉ "/>
	<mfactone_scx_ar row_key="_0V1117HJ9" cproperty="Caption" orgtext="Issued                                                                                                                                                                                                  " orgcol="ariaformset.AriaForm1.lblIssued" langtext="Êã ÅÕÏÇÑå"/>
	<mfactone_scx_ar row_key="_1JS0OGDXW" cproperty="Caption" orgtext="Open                                                                                                                                                                                                    " orgcol="ariaformset.AriaForm1.lblOpen" langtext="ÝÊÍ"/>
	<mfactone_scx_ar row_key="_1JS0PF18P" cproperty="Caption" orgtext="Ok                                                                                                                                                                                                      " orgcol="ariaformset.AriaForm1.cmdOk" langtext="ãæÇÝÞ"/>
	<mfactone_scx_ar row_key="_1JS0PF18Q" cproperty="Caption" orgtext="Cancel                                                                                                                                                                                                  " orgcol="ariaformset.AriaForm1.cmdCancel" langtext="ÅáÛÇÁ"/>
	<mfactone_scx_ar row_key="_1JS0PNPML" cproperty="Caption" orgtext="All open pieces will be canceled                                                                                                                                                                        " orgcol="ariaformset.AriaForm1.lblInfo" langtext="ÓíÊã ÅáÛÇÁ ÌãíÚ ÇáÞØÚ ÇáãÝÊæÍÉ"/>
	<mfactone_scx_ar row_key="_1340OU2UB" cproperty="Caption" orgtext="Actualization Date                                                                                                                                                                                      " orgcol="ariaformset.AriaForm1.lblOperation" langtext="ÊÇÑíÎ ÇáÊÝÚíá"/>
	<mfactone_scx_ar row_key="_0V1117HJ9" cproperty="Caption" orgtext="Budget                                                                                                                                                                                                  " orgcol="ariaformset.AriaForm1.lblBudget" langtext="ãæÇÒäÉ "/>
	<mfactone_scx_ar row_key="_0V1117HJ9" cproperty="Caption" orgtext="Issued                                                                                                                                                                                                  " orgcol="ariaformset.AriaForm1.lblIssued" langtext="Êã ÅÕÏÇÑå"/>
	<mfactone_scx_ar row_key="_1JS0OGDXW" cproperty="Caption" orgtext="Open                                                                                                                                                                                                    " orgcol="ariaformset.AriaForm1.lblOpen" langtext="ÝÊÍ"/>
	<mfactone_scx_ar row_key="_1JS0PF18P" cproperty="Caption" orgtext="Ok                                                                                                                                                                                                      " orgcol="ariaformset.AriaForm1.cmdOk" langtext="ãæÇÝÞ"/>
	<mfactone_scx_ar row_key="_1JS0PF18Q" cproperty="Caption" orgtext="Cancel                                                                                                                                                                                                  " orgcol="ariaformset.AriaForm1.cmdCancel" langtext="ÅáÛÇÁ"/>
	<mfactone_scx_ar row_key="_1JS0PNPML" cproperty="Caption" orgtext="All open pieces will be canceled                                                                                                                                                                        " orgcol="ariaformset.AriaForm1.lblInfo" langtext="ÓíÊã ÅáÛÇÁ ÌãíÚ ÇáÞØÚ ÇáãÝÊæÍÉ"/>
	<mfactone_scx_ar row_key="XX_HEADER_XX" cproperty="MFCSSH.H" orgtext="PRGS\" orgcol="" langtext=""/>
</VFPData>
