<?xml version = "1.0" encoding="Windows-1256" standalone="yes"?>
<VFPData>
	<sucstcon_scx_ar row_key="_0Y313QUBO" cproperty="Caption" orgtext="Connection Information                                                                                                                                                                                  " orgcol="ariaformset.AriaForm1" langtext="ãÚáæãÇÊ ÇáÇÊÕÇá"/>
	<sucstcon_scx_ar row_key="_0Y313QUBQ" cproperty="Caption" orgtext="Connection ID                                                                                                                                                                                           " orgcol="ariaformset.AriaForm1.lblID" langtext="ãÚÑÝ ÇÊÕÇá"/>
	<sucstcon_scx_ar row_key="_0Y313QUBU" cproperty="Caption" orgtext="Connection Type                                                                                                                                                                                         " orgcol="ariaformset.AriaForm1.lblType" langtext="äæÚ ÇáÇÊÕÇá"/>
	<sucstcon_scx_ar row_key="_0Y313QUBV" cproperty="Caption" orgtext="Connection Detail                                                                                                                                                                                       " orgcol="ariaformset.AriaForm1.lblDet" langtext="ÊÝÇÕíá ÇáÇÊÕÇá"/>
	<sucstcon_scx_ar row_key="_0Y313QUBY" cproperty="Caption" orgtext="Ok                                                                                                                                                                                                      " orgcol="ariaformset.AriaForm1.cmdOk" langtext="ãæÇÝÞ"/>
	<sucstcon_scx_ar row_key="_0Y313QUBN" cproperty="Caption" orgtext="Cancel                                                                                                                                                                                                  " orgcol="ariaformset.AriaForm1.cmdCancel" langtext="ÅáÛÇÁ"/>
	<sucstcon_scx_ar row_key="_0Y313QUC5" cproperty="Caption" orgtext="Domain                                                                                                                                                                                                  " orgcol="ariaformset.AriaForm1.lblDomain" langtext="ãÌÇá"/>
	<sucstcon_scx_ar row_key="_0Y313QUC4" cproperty="Caption" orgtext="Password                                                                                                                                                                                                " orgcol="ariaformset.AriaForm1.lblPass" langtext="ßáãÉ ÇáãÑæÑ"/>
	<sucstcon_scx_ar row_key="_0Y313QUC0" cproperty="Caption" orgtext="User ID                                                                                                                                                                                                 " orgcol="ariaformset.AriaForm1.lblUserid" langtext="ãÚÑÝ ÇáãÓÊÎÏã"/>
</VFPData>
