<?xml version = "1.0" encoding="Windows-1256" standalone="yes"?>
<VFPData>
	<sodepcrd_h_ar row_key="LANG_COLOrder" cproperty="Caption" orgtext="Order#                                                                                                                                                                                                  " orgcol="LANG_COLOrder" langtext="ÑÞã ÇáÃãÑ"/>
	<sodepcrd_h_ar row_key="LANG_COLStatus" cproperty="Caption" orgtext="Status                                                                                                                                                                                                  " orgcol="LANG_COLStatus" langtext="ÇáÍÇáÉ"/>
	<sodepcrd_h_ar row_key="LANG_COLAccount" cproperty="Caption" orgtext="Account                                                                                                                                                                                                 " orgcol="LANG_COLAccount" langtext="ÍÓÇÈ"/>
	<sodepcrd_h_ar row_key="LANG_COLStore" cproperty="Caption" orgtext="Store                                                                                                                                                                                                   " orgcol="LANG_COLStore" langtext="ÇáãÎÒä"/>
	<sodepcrd_h_ar row_key="LANG_COLname" cproperty="Caption" orgtext="Name                                                                                                                                                                                                    " orgcol="LANG_COLname" langtext="ÇáÇÓã"/>
	<sodepcrd_h_ar row_key="LANG_COLDept" cproperty="Caption" orgtext="Department                                                                                                                                                                                              " orgcol="LANG_COLDept" langtext="ÅÏÇÑÉ"/>
	<sodepcrd_h_ar row_key="LANG_COLMultiPo" cproperty="Caption" orgtext="Multi PO                                                                                                                                                                                                " orgcol="LANG_COLMultiPo" langtext="ÃãÑ ÔÑÇÁ ãÊÚÏÏ"/>
	<sodepcrd_h_ar row_key="LANG_COLCustPo" cproperty="Caption" orgtext="Cust. P.O#                                                                                                                                                                                              " orgcol="LANG_COLCustPo" langtext="ÊÎÕíÕ ÃãÑ ÔÑÇÁ ÑÞã"/>
	<sodepcrd_h_ar row_key="LANG_COLBulk" cproperty="Caption" orgtext="Bulk                                                                                                                                                                                                    " orgcol="LANG_COLBulk" langtext="ÔÍäÉ"/>
	<sodepcrd_h_ar row_key="LANG_COLMulti" cproperty="Caption" orgtext="Multi                                                                                                                                                                                                   " orgcol="LANG_COLMulti" langtext="ãÊÚÏÏ"/>
	<sodepcrd_h_ar row_key="LANG_COLcFacCode" cproperty="Caption" orgtext="Factor Code                                                                                                                                                                                             " orgcol="LANG_COLcFacCode" langtext="ßæÏ ÇáÚÇãá"/>
	<sodepcrd_h_ar row_key="LANG_COLRep1" cproperty="Caption" orgtext="Sales Rep1                                                                                                                                                                                              " orgcol="LANG_COLRep1" langtext="ãäÏæÈ ãÈíÚÇÊ1"/>
	<sodepcrd_h_ar row_key="LANG_COLComm1" cproperty="Caption" orgtext="Commission 1                                                                                                                                                                                            " orgcol="LANG_COLComm1" langtext="ÚãæáÉ1"/>
	<sodepcrd_h_ar row_key="LANG_COLRep2" cproperty="Caption" orgtext="Sales Rep2                                                                                                                                                                                              " orgcol="LANG_COLRep2" langtext="ãäÏæÈ ãÈíÚÇÊ 2"/>
	<sodepcrd_h_ar row_key="LANG_COLComm2" cproperty="Caption" orgtext="Commission 2                                                                                                                                                                                            " orgcol="LANG_COLComm2" langtext="ÚãæáÉ2"/>
	<sodepcrd_h_ar row_key="LANG_COLOpen" cproperty="Caption" orgtext="Open.Qty.                                                                                                                                                                                               " orgcol="LANG_COLOpen" langtext="ÇáßãíÉ ÇáÇÝÊÊÇÍíÉ"/>
	<sodepcrd_h_ar row_key="LANG_COLOpenAmt" cproperty="Caption" orgtext="Open.Amt.                                                                                                                                                                                               " orgcol="LANG_COLOpenAmt" langtext="ÇáÑÕíÏ ÇáÇÝÊÊÇÍí"/>
	<sodepcrd_h_ar row_key="LANG_COLShip" cproperty="Caption" orgtext="Ship.Qty.                                                                                                                                                                                               " orgcol="LANG_COLShip" langtext="ßãíÉ ÇáÔÍä"/>
	<sodepcrd_h_ar row_key="LANG_COLShipAmt" cproperty="Caption" orgtext="Ship.Amt.                                                                                                                                                                                               " orgcol="LANG_COLShipAmt" langtext="ãÈáÛ ÇáÔÍä"/>
	<sodepcrd_h_ar row_key="LANG_COLBook" cproperty="Caption" orgtext="Book.Qty.                                                                                                                                                                                               " orgcol="LANG_COLBook" langtext="ÇáßãíÉ ÇáãÍÌæÒÉ"/>
	<sodepcrd_h_ar row_key="LANG_COLBookAmt" cproperty="Caption" orgtext="Book.Amt.                                                                                                                                                                                               " orgcol="LANG_COLBookAmt" langtext="ÇáãÈáÛ ÇáãÍÌæÒ"/>
	<sodepcrd_h_ar row_key="LANG_COLCancel" cproperty="Caption" orgtext="Cancel.Qty.                                                                                                                                                                                             " orgcol="LANG_COLCancel" langtext="ÅáÛÇÁ ÇáßãíÉ"/>
	<sodepcrd_h_ar row_key="LANG_COLCancelAmt" cproperty="Caption" orgtext="Cancel.Amt.                                                                                                                                                                                             " orgcol="LANG_COLCancelAmt" langtext="ÅáÛÇÁ ÇáãÈáÛ"/>
	<sodepcrd_h_ar row_key="LANG_COLEntered" cproperty="Caption" orgtext="Entered                                                                                                                                                                                                 " orgcol="LANG_COLEntered" langtext="Êã ÅÏÎÇáå"/>
	<sodepcrd_h_ar row_key="LANG_COLStart" cproperty="Caption" orgtext="Start                                                                                                                                                                                                   " orgcol="LANG_COLStart" langtext="ÈÏÁ ÊÔÛíá"/>
	<sodepcrd_h_ar row_key="LANG_COLComplete" cproperty="Caption" orgtext="Complete                                                                                                                                                                                                " orgcol="LANG_COLComplete" langtext="ÇÓÊßãÇá"/>
	<sodepcrd_h_ar row_key="LANG_COLCancelled" cproperty="Caption" orgtext="Cancelled                                                                                                                                                                                               " orgcol="LANG_COLCancelled" langtext="ãáÛí"/>
	<sodepcrd_h_ar row_key="LANG_COLDisc" cproperty="Caption" orgtext="Disc.                                                                                                                                                                                                   " orgcol="LANG_COLDisc" langtext="ÎÕã"/>
	<sodepcrd_h_ar row_key="LANG_COLcWareCode" cproperty="Caption" orgtext="Warehouse                                                                                                                                                                                               " orgcol="LANG_COLcWareCode" langtext="ãÓÊæÏÚ"/>
	<sodepcrd_h_ar row_key="LANG_COLcAdd_User" cproperty="Caption" orgtext="User                                                                                                                                                                                                    " orgcol="LANG_COLcAdd_User" langtext="ÇáãÓÊÎÏã"/>
	<sodepcrd_h_ar row_key="LANG_COLdAdd_Date" cproperty="Caption" orgtext="Date                                                                                                                                                                                                    " orgcol="LANG_COLdAdd_Date" langtext="ÇáÊÇÑíÎ"/>
	<sodepcrd_h_ar row_key="LANG_COLSeason" cproperty="Caption" orgtext="Season                                                                                                                                                                                                  " orgcol="LANG_COLSeason" langtext="ãæÓã"/>
	<sodepcrd_h_ar row_key="LANG_COLDivision" cproperty="Caption" orgtext="Division                                                                                                                                                                                                " orgcol="LANG_COLDivision" langtext="ÞÓã"/>
	<sodepcrd_h_ar row_key="LANG_COLShipVia" cproperty="Caption" orgtext="ShipVia                                                                                                                                                                                                 " orgcol="LANG_COLShipVia" langtext="ÇáÔÍä Úä ØÑíÞ"/>
	<sodepcrd_h_ar row_key="LANG_COLNote1" cproperty="Caption" orgtext="Notes 1                                                                                                                                                                                                 " orgcol="LANG_COLNote1" langtext="ãáÇÍÙÇÊ 1"/>
	<sodepcrd_h_ar row_key="LANG_COLNote2" cproperty="Caption" orgtext="Notes 2                                                                                                                                                                                                 " orgcol="LANG_COLNote2" langtext="ãáÇÍÙÇÊ 2"/>
	<sodepcrd_h_ar row_key="LANG_Trans" cproperty="Caption" orgtext="Transaction#                                                                                                                                                                                            " orgcol="LANG_Trans" langtext="ÑÞã ÇáãÚÇãáÉ"/>
	<sodepcrd_h_ar row_key="LANG_Batch" cproperty="Caption" orgtext="Batch#                                                                                                                                                                                                  " orgcol="LANG_Batch" langtext="ÑÞã ÇáÏÝÚÉ"/>
	<sodepcrd_h_ar row_key="LANG_TransDate" cproperty="Caption" orgtext="Date                                                                                                                                                                                                    " orgcol="LANG_TransDate" langtext="ÇáÊÇÑíÎ"/>
	<sodepcrd_h_ar row_key="LANG_Amount" cproperty="Caption" orgtext="Amount                                                                                                                                                                                                  " orgcol="LANG_Amount" langtext="ÇáãÈáÛ"/>
	<sodepcrd_h_ar row_key="LANG_Credit" cproperty="Caption" orgtext="Credits                                                                                                                                                                                                 " orgcol="LANG_Credit" langtext="ÅÖÇÝÇÊ"/>
	<sodepcrd_h_ar row_key="LANG_Ord_titles" cproperty="Caption" orgtext="Orders                                                                                                                                                                                                  " orgcol="LANG_Ord_titles" langtext="ÃæÇãÑ"/>
	<sodepcrd_h_ar row_key="LANG_Dep_Amt" cproperty="Caption" orgtext="Deposit Amount:                                                                                                                                                                                         " orgcol="LANG_Dep_Amt" langtext="ãÈáÛ ÇáÅíÏÇÚ:"/>
	<sodepcrd_h_ar row_key="LANG_Order_lbl" cproperty="Caption" orgtext="Order#              :                                                                                                                                                                                   " orgcol="LANG_Order_lbl" langtext="ÑÞã ÇáÃãÑ:"/>
	<sodepcrd_h_ar row_key="LANG_Cust_po" cproperty="Caption" orgtext="Cust. PO  	   :                                                                                                                                                                                         " orgcol="LANG_Cust_po" langtext="ÊÎÕíÕ ÃãÑ ÔÑÇÁ:"/>
	<sodepcrd_h_ar row_key="LANG_Start_lbl" cproperty="Caption" orgtext="Start          :                                                                                                                                                                                        " orgcol="LANG_Start_lbl" langtext="ÈÏÁ ÊÔÛíá:"/>
	<sodepcrd_h_ar row_key="LANG_op_amt" cproperty="Caption" orgtext="Open Amount     :                                                                                                                                                                                       " orgcol="LANG_op_amt" langtext="ÇáãÈáÛ ÇáÇÝÊÊÇÍí:"/>
	<sodepcrd_h_ar row_key="LANG_Comp_lbl" cproperty="Caption" orgtext="Complete    :                                                                                                                                                                                           " orgcol="LANG_Comp_lbl" langtext="ÇÓÊßãÇá:"/>
	<sodepcrd_h_ar row_key="LANG_Cust_grid" cproperty="Caption" orgtext="Customer PO                                                                                                                                                                                             " orgcol="LANG_Cust_grid" langtext="ÃãÑ ÔÑÇÁ ÇáÚãíá"/>
	<sodepcrd_h_ar row_key="LANG_Start_grid" cproperty="Caption" orgtext="Start                                                                                                                                                                                                   " orgcol="LANG_Start_grid" langtext="ÈÏÁ ÊÔÛíá"/>
	<sodepcrd_h_ar row_key="LANG_Comp_grid" cproperty="Caption" orgtext="Complete                                                                                                                                                                                                " orgcol="LANG_Comp_grid" langtext="ÇÓÊßãÇá"/>
	<sodepcrd_h_ar row_key="LANG_opamt_grid" cproperty="Caption" orgtext="Order Amount                                                                                                                                                                                            " orgcol="LANG_opamt_grid" langtext="ãÈáÛ ÇáÃãÑ"/>
	<sodepcrd_h_ar row_key="LANG_Deposit_Amt" cproperty="Caption" orgtext="Deposit Amount                                                                                                                                                                                          " orgcol="LANG_Deposit_Amt" langtext="ãÈáÛ ÇáÅíÏÇÚ"/>
	<sodepcrd_h_ar row_key="LANG_Tot_Deposit_Amt" cproperty="Caption" orgtext="Total Order Deposits                                                                                                                                                                                    " orgcol="LANG_Tot_Deposit_Amt" langtext="ÅÌãÇáí ÇáæÏÇÆÚ ÇáÃãÑ"/>
	<sodepcrd_h_ar row_key="LANG_COLORDER" cproperty="Caption" orgtext="Order#                                                                                                                                                                                                  " orgcol="LANG_COLORDER" langtext="ÑÞã ÇáÃãÑ"/>
	<sodepcrd_h_ar row_key="LANG_COLSTATUS" cproperty="Caption" orgtext="Status                                                                                                                                                                                                  " orgcol="LANG_COLSTATUS" langtext="ÇáÍÇáÉ"/>
	<sodepcrd_h_ar row_key="LANG_COLACCOUNT" cproperty="Caption" orgtext="Account                                                                                                                                                                                                 " orgcol="LANG_COLACCOUNT" langtext="ÍÓÇÈ"/>
	<sodepcrd_h_ar row_key="LANG_COLSTORE" cproperty="Caption" orgtext="Store                                                                                                                                                                                                   " orgcol="LANG_COLSTORE" langtext="ÇáãÎÒä"/>
	<sodepcrd_h_ar row_key="LANG_COLNAME" cproperty="Caption" orgtext="Name                                                                                                                                                                                                    " orgcol="LANG_COLNAME" langtext="ÇáÇÓã"/>
	<sodepcrd_h_ar row_key="LANG_COLDEPT" cproperty="Caption" orgtext="Department                                                                                                                                                                                              " orgcol="LANG_COLDEPT" langtext="ÅÏÇÑÉ"/>
	<sodepcrd_h_ar row_key="LANG_COLMULTIPO" cproperty="Caption" orgtext="Multi PO                                                                                                                                                                                                " orgcol="LANG_COLMULTIPO" langtext="ÃãÑ ÔÑÇÁ ãÊÚÏÏ"/>
	<sodepcrd_h_ar row_key="LANG_COLCUSTPO" cproperty="Caption" orgtext="Cust. P.O#                                                                                                                                                                                              " orgcol="LANG_COLCUSTPO" langtext="ÊÎÕíÕ ÃãÑ ÔÑÇÁ ÑÞã"/>
	<sodepcrd_h_ar row_key="LANG_COLBULK" cproperty="Caption" orgtext="Bulk                                                                                                                                                                                                    " orgcol="LANG_COLBULK" langtext="ÔÍäÉ"/>
	<sodepcrd_h_ar row_key="LANG_COLMULTI" cproperty="Caption" orgtext="Multi                                                                                                                                                                                                   " orgcol="LANG_COLMULTI" langtext="ãÊÚÏÏ"/>
	<sodepcrd_h_ar row_key="LANG_COLCFACCODE" cproperty="Caption" orgtext="Factor Code                                                                                                                                                                                             " orgcol="LANG_COLCFACCODE" langtext="ßæÏ ÇáÚÇãá"/>
	<sodepcrd_h_ar row_key="LANG_COLREP1" cproperty="Caption" orgtext="Sales Rep1                                                                                                                                                                                              " orgcol="LANG_COLREP1" langtext="ãäÏæÈ ãÈíÚÇÊ1"/>
	<sodepcrd_h_ar row_key="LANG_COLCOMM1" cproperty="Caption" orgtext="Commission 1                                                                                                                                                                                            " orgcol="LANG_COLCOMM1" langtext="ÚãæáÉ1"/>
	<sodepcrd_h_ar row_key="LANG_COLREP2" cproperty="Caption" orgtext="Sales Rep2                                                                                                                                                                                              " orgcol="LANG_COLREP2" langtext="ãäÏæÈ ãÈíÚÇÊ 2"/>
	<sodepcrd_h_ar row_key="LANG_COLCOMM2" cproperty="Caption" orgtext="Commission 2                                                                                                                                                                                            " orgcol="LANG_COLCOMM2" langtext="ÚãæáÉ2"/>
	<sodepcrd_h_ar row_key="LANG_COLOPEN" cproperty="Caption" orgtext="Open.Qty.                                                                                                                                                                                               " orgcol="LANG_COLOPEN" langtext="ÇáßãíÉ ÇáÇÝÊÊÇÍíÉ"/>
	<sodepcrd_h_ar row_key="LANG_COLOPENAMT" cproperty="Caption" orgtext="Open.Amt.                                                                                                                                                                                               " orgcol="LANG_COLOPENAMT" langtext="ÇáÑÕíÏ ÇáÇÝÊÊÇÍí"/>
	<sodepcrd_h_ar row_key="LANG_COLSHIP" cproperty="Caption" orgtext="Ship.Qty.                                                                                                                                                                                               " orgcol="LANG_COLSHIP" langtext="ßãíÉ ÇáÔÍä"/>
	<sodepcrd_h_ar row_key="LANG_COLSHIPAMT" cproperty="Caption" orgtext="Ship.Amt.                                                                                                                                                                                               " orgcol="LANG_COLSHIPAMT" langtext="ãÈáÛ ÇáÔÍä"/>
	<sodepcrd_h_ar row_key="LANG_COLBOOK" cproperty="Caption" orgtext="Book.Qty.                                                                                                                                                                                               " orgcol="LANG_COLBOOK" langtext="ÇáßãíÉ ÇáãÍÌæÒÉ"/>
	<sodepcrd_h_ar row_key="LANG_COLBOOKAMT" cproperty="Caption" orgtext="Book.Amt.                                                                                                                                                                                               " orgcol="LANG_COLBOOKAMT" langtext="ÇáãÈáÛ ÇáãÍÌæÒ"/>
	<sodepcrd_h_ar row_key="LANG_COLCANCEL" cproperty="Caption" orgtext="Cancel.Qty.                                                                                                                                                                                             " orgcol="LANG_COLCANCEL" langtext="ÅáÛÇÁ ÇáßãíÉ"/>
	<sodepcrd_h_ar row_key="LANG_COLCANCELAMT" cproperty="Caption" orgtext="Cancel.Amt.                                                                                                                                                                                             " orgcol="LANG_COLCANCELAMT" langtext="ÅáÛÇÁ ÇáãÈáÛ"/>
	<sodepcrd_h_ar row_key="LANG_COLENTERED" cproperty="Caption" orgtext="Entered                                                                                                                                                                                                 " orgcol="LANG_COLENTERED" langtext="Êã ÅÏÎÇáå"/>
	<sodepcrd_h_ar row_key="LANG_COLSTART" cproperty="Caption" orgtext="Start                                                                                                                                                                                                   " orgcol="LANG_COLSTART" langtext="ÈÏÁ ÊÔÛíá"/>
	<sodepcrd_h_ar row_key="LANG_COLCOMPLETE" cproperty="Caption" orgtext="Complete                                                                                                                                                                                                " orgcol="LANG_COLCOMPLETE" langtext="ÇÓÊßãÇá"/>
	<sodepcrd_h_ar row_key="LANG_COLCANCELLED" cproperty="Caption" orgtext="Cancelled                                                                                                                                                                                               " orgcol="LANG_COLCANCELLED" langtext="ãáÛí"/>
	<sodepcrd_h_ar row_key="LANG_COLDISC" cproperty="Caption" orgtext="Disc.                                                                                                                                                                                                   " orgcol="LANG_COLDISC" langtext="ÎÕã"/>
	<sodepcrd_h_ar row_key="LANG_COLCWARECODE" cproperty="Caption" orgtext="Warehouse                                                                                                                                                                                               " orgcol="LANG_COLCWARECODE" langtext="ãÓÊæÏÚ"/>
	<sodepcrd_h_ar row_key="LANG_COLCADD_USER" cproperty="Caption" orgtext="User                                                                                                                                                                                                    " orgcol="LANG_COLCADD_USER" langtext="ÇáãÓÊÎÏã"/>
	<sodepcrd_h_ar row_key="LANG_COLDADD_DATE" cproperty="Caption" orgtext="Date                                                                                                                                                                                                    " orgcol="LANG_COLDADD_DATE" langtext="ÇáÊÇÑíÎ"/>
	<sodepcrd_h_ar row_key="LANG_COLSEASON" cproperty="Caption" orgtext="Season                                                                                                                                                                                                  " orgcol="LANG_COLSEASON" langtext="ãæÓã"/>
	<sodepcrd_h_ar row_key="LANG_COLDIVISION" cproperty="Caption" orgtext="Division                                                                                                                                                                                                " orgcol="LANG_COLDIVISION" langtext="ÞÓã"/>
	<sodepcrd_h_ar row_key="LANG_COLSHIPVIA" cproperty="Caption" orgtext="ShipVia                                                                                                                                                                                                 " orgcol="LANG_COLSHIPVIA" langtext="ÇáÔÍä Úä ØÑíÞ"/>
	<sodepcrd_h_ar row_key="LANG_COLNOTE1" cproperty="Caption" orgtext="Notes 1                                                                                                                                                                                                 " orgcol="LANG_COLNOTE1" langtext="ãáÇÍÙÇÊ 1"/>
	<sodepcrd_h_ar row_key="LANG_COLNOTE2" cproperty="Caption" orgtext="Notes 2                                                                                                                                                                                                 " orgcol="LANG_COLNOTE2" langtext="ãáÇÍÙÇÊ 2"/>
	<sodepcrd_h_ar row_key="LANG_TRANS" cproperty="Caption" orgtext="Transaction#                                                                                                                                                                                            " orgcol="LANG_TRANS" langtext="ÑÞã ÇáãÚÇãáÉ"/>
	<sodepcrd_h_ar row_key="LANG_BATCH" cproperty="Caption" orgtext="Batch#                                                                                                                                                                                                  " orgcol="LANG_BATCH" langtext="ÑÞã ÇáÏÝÚÉ"/>
	<sodepcrd_h_ar row_key="LANG_TRANSDATE" cproperty="Caption" orgtext="Date                                                                                                                                                                                                    " orgcol="LANG_TRANSDATE" langtext="ÇáÊÇÑíÎ"/>
	<sodepcrd_h_ar row_key="LANG_AMOUNT" cproperty="Caption" orgtext="Amount                                                                                                                                                                                                  " orgcol="LANG_AMOUNT" langtext="ÇáãÈáÛ"/>
	<sodepcrd_h_ar row_key="LANG_CREDIT" cproperty="Caption" orgtext="Credits                                                                                                                                                                                                 " orgcol="LANG_CREDIT" langtext="ÅÖÇÝÇÊ"/>
	<sodepcrd_h_ar row_key="LANG_ORD_TITLES" cproperty="Caption" orgtext="Orders                                                                                                                                                                                                  " orgcol="LANG_ORD_TITLES" langtext="ÃæÇãÑ"/>
	<sodepcrd_h_ar row_key="LANG_DEP_AMT" cproperty="Caption" orgtext="Deposit Amount:                                                                                                                                                                                         " orgcol="LANG_DEP_AMT" langtext="ãÈáÛ ÇáÅíÏÇÚ:"/>
	<sodepcrd_h_ar row_key="LANG_ORDER_LBL" cproperty="Caption" orgtext="Order#              :                                                                                                                                                                                   " orgcol="LANG_ORDER_LBL" langtext="ÑÞã ÇáÃãÑ:"/>
	<sodepcrd_h_ar row_key="LANG_CUST_PO" cproperty="Caption" orgtext="Cust. PO  	   :                                                                                                                                                                                         " orgcol="LANG_CUST_PO" langtext="ÊÎÕíÕ ÃãÑ ÔÑÇÁ:"/>
	<sodepcrd_h_ar row_key="LANG_START_LBL" cproperty="Caption" orgtext="Start          :                                                                                                                                                                                        " orgcol="LANG_START_LBL" langtext="ÈÏÁ ÊÔÛíá:"/>
	<sodepcrd_h_ar row_key="LANG_OP_AMT" cproperty="Caption" orgtext="Open Amount     :                                                                                                                                                                                       " orgcol="LANG_OP_AMT" langtext="ÇáãÈáÛ ÇáÇÝÊÊÇÍí:"/>
	<sodepcrd_h_ar row_key="LANG_COMP_LBL" cproperty="Caption" orgtext="Complete    :                                                                                                                                                                                           " orgcol="LANG_COMP_LBL" langtext="ÇÓÊßãÇá:"/>
	<sodepcrd_h_ar row_key="LANG_CUST_GRID" cproperty="Caption" orgtext="Customer PO                                                                                                                                                                                             " orgcol="LANG_CUST_GRID" langtext="ÃãÑ ÔÑÇÁ ÇáÚãíá"/>
	<sodepcrd_h_ar row_key="LANG_START_GRID" cproperty="Caption" orgtext="Start                                                                                                                                                                                                   " orgcol="LANG_START_GRID" langtext="ÈÏÁ ÊÔÛíá"/>
	<sodepcrd_h_ar row_key="LANG_COMP_GRID" cproperty="Caption" orgtext="Complete                                                                                                                                                                                                " orgcol="LANG_COMP_GRID" langtext="ÇÓÊßãÇá"/>
	<sodepcrd_h_ar row_key="LANG_OPAMT_GRID" cproperty="Caption" orgtext="Order Amount                                                                                                                                                                                            " orgcol="LANG_OPAMT_GRID" langtext="ãÈáÛ ÇáÃãÑ"/>
	<sodepcrd_h_ar row_key="LANG_DEPOSIT_AMT" cproperty="Caption" orgtext="Deposit Amount                                                                                                                                                                                          " orgcol="LANG_DEPOSIT_AMT" langtext="ãÈáÛ ÇáÅíÏÇÚ"/>
	<sodepcrd_h_ar row_key="LANG_TOT_DEPOSIT_AMT" cproperty="Caption" orgtext="Total Order Deposits                                                                                                                                                                                    " orgcol="LANG_TOT_DEPOSIT_AMT" langtext="ÅÌãÇáí ÇáæÏÇÆÚ ÇáÃãÑ"/>
	<sodepcrd_h_ar row_key="LANG_COLREF" cproperty="Caption" orgtext="Reference                                                                                                                                                                                               " orgcol="LANG_COLREF" langtext="ãÑÌÚ"/>
	<sodepcrd_h_ar row_key="LANG_COLDESD" cproperty="Caption" orgtext="Description                                                                                                                                                                                             " orgcol="LANG_COLDESD" langtext="æÕÝ"/>
</VFPData>
